{
	"configurations" : 
	[
		{
			"abstractTargets" : 
			[
				{
					"directoryIndex" : 0,
					"id" : "Python3::Interpreter::@6890427a1f51a3e7e1df",
					"jsonFile" : "target-Python3__Interpreter-Release-964c8980d71e77be1b7d.json",
					"name" : "Python3::Interpreter",
					"projectIndex" : 0
				},
				{
					"directoryIndex" : 0,
					"id" : "Python3::InterpreterMultiConfig::@6890427a1f51a3e7e1df",
					"jsonFile" : "target-Python3__InterpreterMultiConfig-Release-c9145b219e8408fbc688.json",
					"name" : "Python3::InterpreterMultiConfig",
					"projectIndex" : 0
				},
				{
					"directoryIndex" : 0,
					"id" : "pybind11::embed::@6890427a1f51a3e7e1df",
					"jsonFile" : "target-pybind11__embed-Release-9088ee9b43793483d8b1.json",
					"name" : "pybind11::embed",
					"projectIndex" : 0
				},
				{
					"directoryIndex" : 0,
					"id" : "pybind11::headers::@6890427a1f51a3e7e1df",
					"jsonFile" : "target-pybind11__headers-Release-8169abe5db6f931bb936.json",
					"name" : "pybind11::headers",
					"projectIndex" : 0
				},
				{
					"directoryIndex" : 0,
					"id" : "pybind11::lto::@6890427a1f51a3e7e1df",
					"jsonFile" : "target-pybind11__lto-Release-768b47717fa7130c8bf9.json",
					"name" : "pybind11::lto",
					"projectIndex" : 0
				},
				{
					"directoryIndex" : 0,
					"id" : "pybind11::module::@6890427a1f51a3e7e1df",
					"jsonFile" : "target-pybind11__module-Release-c67aa9483c73f896096a.json",
					"name" : "pybind11::module",
					"projectIndex" : 0
				},
				{
					"directoryIndex" : 0,
					"id" : "pybind11::opt_size::@6890427a1f51a3e7e1df",
					"jsonFile" : "target-pybind11__opt_size-Release-c1bf415a82122fd060cd.json",
					"name" : "pybind11::opt_size",
					"projectIndex" : 0
				},
				{
					"directoryIndex" : 0,
					"id" : "pybind11::pybind11::@6890427a1f51a3e7e1df",
					"jsonFile" : "target-pybind11__pybind11-Release-9e396298c44349e38728.json",
					"name" : "pybind11::pybind11",
					"projectIndex" : 0
				},
				{
					"directoryIndex" : 0,
					"id" : "pybind11::pybind11_headers::@6890427a1f51a3e7e1df",
					"jsonFile" : "target-pybind11__pybind11_headers-Release-163a2fcd88cf2552d4c5.json",
					"name" : "pybind11::pybind11_headers",
					"projectIndex" : 0
				},
				{
					"directoryIndex" : 0,
					"id" : "pybind11::python_link_helper::@6890427a1f51a3e7e1df",
					"jsonFile" : "target-pybind11__python_link_helper-Release-a6d4022c6c91da052ec8.json",
					"name" : "pybind11::python_link_helper",
					"projectIndex" : 0
				},
				{
					"directoryIndex" : 0,
					"id" : "pybind11::thin_lto::@6890427a1f51a3e7e1df",
					"jsonFile" : "target-pybind11__thin_lto-Release-9b292dfca5963db9e06d.json",
					"name" : "pybind11::thin_lto",
					"projectIndex" : 0
				},
				{
					"directoryIndex" : 0,
					"id" : "pybind11::windows_extras::@6890427a1f51a3e7e1df",
					"jsonFile" : "target-pybind11__windows_extras-Release-87b26a174cc90911855f.json",
					"name" : "pybind11::windows_extras",
					"projectIndex" : 0
				}
			],
			"directories" : 
			[
				{
					"abstractTargetIndexes" : 
					[
						0,
						1,
						2,
						3,
						4,
						5,
						6,
						7,
						8,
						9,
						10,
						11
					],
					"build" : ".",
					"hasInstallRule" : true,
					"jsonFile" : "directory-.-Release-398686c778d86f35bfc9.json",
					"minimumCMakeVersion" : 
					{
						"string" : "3.5"
					},
					"projectIndex" : 0,
					"source" : ".",
					"targetIndexes" : 
					[
						0,
						1
					]
				}
			],
			"name" : "Release",
			"projects" : 
			[
				{
					"abstractTargetIndexes" : 
					[
						0,
						1,
						2,
						3,
						4,
						5,
						6,
						7,
						8,
						9,
						10,
						11
					],
					"directoryIndexes" : 
					[
						0
					],
					"name" : "pybind11_vendor",
					"targetIndexes" : 
					[
						0,
						1
					]
				}
			],
			"targets" : 
			[
				{
					"directoryIndex" : 0,
					"id" : "pybind11_vendor_uninstall::@6890427a1f51a3e7e1df",
					"jsonFile" : "target-pybind11_vendor_uninstall-Release-f6d437a3af77973826ce.json",
					"name" : "pybind11_vendor_uninstall",
					"projectIndex" : 0
				},
				{
					"directoryIndex" : 0,
					"id" : "uninstall::@6890427a1f51a3e7e1df",
					"jsonFile" : "target-uninstall-Release-46a765977edc8cca0222.json",
					"name" : "uninstall",
					"projectIndex" : 0
				}
			]
		}
	],
	"kind" : "codemodel",
	"paths" : 
	{
		"build" : "/home/jliang/ros_ws/build/pybind11_vendor",
		"source" : "/home/jliang/ros_ws/src/pybind11_vendor"
	},
	"version" : 
	{
		"major" : 2,
		"minor" : 9
	}
}
